grafog/__init__.py
grafog/transforms/__init__.py
grafog/transforms/transforms.py
grafog-0.1.dist-info/LICENSE
grafog-0.1.dist-info/METADATA
grafog-0.1.dist-info/WHEEL
grafog-0.1.dist-info/top_level.txt
grafog-0.1.dist-info/RECORD
