Metadata-Version: 2.1
Name: grafog
Version: 0.1
Summary: Graph Data Augmentations for PyTorch Geometric
Home-page: https://github.com/rish-16/grafog
Author: Rishabh Anand
Author-email: mail.rishabh.anand@gmail.com
License: MIT
Keywords: machine learning,graph deep learning,data augmentations
Platform: UNKNOWN
Classifier: Development Status :: 4 - Beta
Classifier: Intended Audience :: Developers
Classifier: Topic :: Scientific/Engineering :: Artificial Intelligence
Classifier: License :: OSI Approved :: MIT License
Classifier: Programming Language :: Python :: 3.6
License-File: LICENSE
Requires-Dist: torch (>=1.10)
Requires-Dist: torch-geometric (>=2.0)
